bidirectional_cross_attention_jax/__init__.py
bidirectional_cross_attention_jax/bidirectional_cross_attention_jax.py
bidirectional_cross_attention_jax-0.0.2.dist-info/LICENSE
bidirectional_cross_attention_jax-0.0.2.dist-info/METADATA
bidirectional_cross_attention_jax-0.0.2.dist-info/WHEEL
bidirectional_cross_attention_jax-0.0.2.dist-info/top_level.txt
bidirectional_cross_attention_jax-0.0.2.dist-info/RECORD
