Metadata-Version: 2.1
Name: bidirectional_cross_attention_jax
Version: 0.0.2
Project-URL: Homepage, https://github.com/axrwl/bidirectional-cross-attention
Classifier: Programming Language :: Python :: 3
Classifier: License :: OSI Approved :: MIT License
Requires-Python: >=3.8
License-File: LICENSE
